docinit/__init__.py
docinit/docinit.py
docinit/skeleton/Makefile
docinit/skeleton/conf.py
docinit/skeleton/default.rst
docinit/skeleton/index.rst
docinit/skeleton/make.bat
docinit/skeleton/_ext/includefirst.py
docinit/skeleton/_static/back.js
docinit/skeleton/_static/docinit.css
docinit/skeleton/_templates/breadcrumbs.html
docinit/skeleton/_templates/footer.html
docinit/skeleton/_templates/layout.html
docinit/skeleton/_templates/autoapi/index.rst
docinit/skeleton/_templates/autoapi/python/module.rst
docinit-0.19.dist-info/LICENSE
docinit-0.19.dist-info/METADATA
docinit-0.19.dist-info/WHEEL
docinit-0.19.dist-info/entry_points.txt
docinit-0.19.dist-info/top_level.txt
docinit-0.19.dist-info/RECORD
