Metadata-Version: 2.1
Name: docinit
Version: 0.19
Summary: Bootstrap your Sphinx documentation
Home-page: https://github.com/timeflux/docinit
Author: Pierre Clisson
Author-email: contact@timeflux.io
License: MIT
Project-URL: Source Code, https://github.com/mesca/docinit
Project-URL: Bug Tracker, https://github.com/mesca/docinit/issues
Keywords: doc,autodoc,sphinx,apidoc
Classifier: License :: OSI Approved :: MIT License
Classifier: Programming Language :: Python
Classifier: Operating System :: OS Independent
Classifier: Intended Audience :: Developers
Classifier: Topic :: Documentation :: Sphinx
License-File: LICENSE
Requires-Dist: setuptools (>=62)
Requires-Dist: setuptools-scm (>=3.5)
Requires-Dist: sphinx (>=2.2)
Requires-Dist: sphinx-rtd-theme (>=0.4)
Requires-Dist: sphinx-autoapi (>=1.3)
